hlfbt/serial_console/__init__.py
hlfbt/serial_console/__main__.py
hlfbt/serial_console/cli.py
hlfbt/serial_console/_argparse/__init__.py
hlfbt/serial_console/_argparse/formatter.py
hlfbt/serial_console/console/__init__.py
hlfbt/serial_console/console/console.py
hlfbt/serial_console/console/io.py
hlfbt/serial_console/console/matching.py
hlfbt_serial_console-0.0.6.dist-info/LICENSE
hlfbt_serial_console-0.0.6.dist-info/METADATA
hlfbt_serial_console-0.0.6.dist-info/WHEEL
hlfbt_serial_console-0.0.6.dist-info/entry_points.txt
hlfbt_serial_console-0.0.6.dist-info/top_level.txt
hlfbt_serial_console-0.0.6.dist-info/RECORD
