Metadata-Version: 2.1
Name: hlfbt-serial-console
Version: 0.0.6
Summary: A simple utility to interface with prompt-like (serial) consoles
Home-page: https://github.com/hlfbt/serial-console
Author: Alexander Schulz
Author-email: alex@nope.bz
License: UNKNOWN
Platform: UNKNOWN
Classifier: Programming Language :: Python :: 3
Classifier: License :: OSI Approved :: MIT License
Classifier: Development Status :: 3 - Alpha
Classifier: Operating System :: POSIX
Classifier: Operating System :: Microsoft :: Windows
Classifier: Operating System :: MacOS :: MacOS X
Classifier: Topic :: Communications
Classifier: Topic :: Terminals :: Serial
Requires-Python: >=3.5
License-File: LICENSE
Requires-Dist: pyserial
